ljse/__init__.py
ljse/history.py
ljse/tickers.py
ljse-0.1.5.dist-info/licenses/LICENSE.txt
ljse-0.1.5.dist-info/METADATA
ljse-0.1.5.dist-info/WHEEL
ljse-0.1.5.dist-info/top_level.txt
ljse-0.1.5.dist-info/RECORD
