Metadata-Version: 2.4
Name: LJSE
Version: 0.1.5
Summary: Client for Ljubljana Stock Exchange REST API
Author-email: Janez Bucar <gospod.bucarrr@gmail.com>
Requires-Python: >=3.11
License-File: LICENSE.txt
Requires-Dist: pandas
Requires-Dist: tqdm
Dynamic: license-file
